archaeo_summarizer/__init__.py
archaeo_summarizer/main.py
archaeo_summarizer/prompts.py
archaeo_summarizer-2025.12.21192749.dist-info/METADATA
archaeo_summarizer-2025.12.21192749.dist-info/WHEEL
archaeo_summarizer-2025.12.21192749.dist-info/top_level.txt
archaeo_summarizer-2025.12.21192749.dist-info/RECORD
