Metadata-Version: 2.4
Name: archaeo-summarizer
Version: 2025.12.21192749
Summary: archaeo-summarizer extracts structured summaries from archaeological and historical texts, highlighting key findings and cultural developments for efficient research.
Author-email: archaeo-summarizer <hi@eugene.plus>
License: MIT
Project-URL: Homepage, https://github.com/chigwell/archaeo-summarizer
Requires-Python: >=3.9
Requires-Dist: langchain-llm7>=0.0.0
Requires-Dist: llmatch-messages>=0.0.0
Requires-Dist: langchain-core>=0.3.0
